cfly/__init__.py
cfly/core.py
cfly/data.py
cfly-1.0.3.dist-info/DESCRIPTION.rst
cfly-1.0.3.dist-info/METADATA
cfly-1.0.3.dist-info/RECORD
cfly-1.0.3.dist-info/WHEEL
cfly-1.0.3.dist-info/metadata.json
cfly-1.0.3.dist-info/top_level.txt
