Metadata-Version: 2.0
Name: cfly
Version: 1.0.3
Summary: Build python extensions on-the-fly. Run C++ code directly from Python
Home-page: https://github.com/pymet/cfly
Author: pymet
Author-email: office@pymet.com
License: MIT
Keywords: cfly,build,extension,c++
Platform: UNKNOWN
Requires-Dist: jinja2
